stashhouse/__init__.py
stashhouse/__main__.py
stashhouse/cli.py
stashhouse/plugin.py
stashhouse/server.py
stashhouse-0.0.4.dist-info/METADATA
stashhouse-0.0.4.dist-info/WHEEL
stashhouse-0.0.4.dist-info/entry_points.txt
stashhouse-0.0.4.dist-info/licenses/LICENSE
stashhouse-0.0.4.dist-info/RECORD
