Metadata-Version: 2.4
Name: stashhouse
Version: 0.0.4
Summary: Centrally store files from a variety of protocols.
Project-URL: Homepage, https://github.com/Jayson-Fong/stashhouse
Project-URL: Issues, https://github.com/Jayson-Fong/stashhouse/issues
Author-email: Jayson Fong <jayson.fong@gatech.edu>
License-Expression: MIT
License-File: LICENSE
Classifier: Development Status :: 1 - Planning
Classifier: License :: OSI Approved :: MIT License
Classifier: Operating System :: OS Independent
Classifier: Programming Language :: Python
Classifier: Programming Language :: Python :: 3.11
Classifier: Programming Language :: Python :: 3.12
Classifier: Programming Language :: Python :: 3.13
Classifier: Topic :: Communications :: File Sharing
Classifier: Typing :: Typed
Requires-Python: >=3.11
Provides-Extra: ssh
Requires-Dist: stashhouse-ssh>=0.0.5; extra == 'ssh'
Provides-Extra: tftp
Requires-Dist: stashhouse-tftp>=0.0.2; extra == 'tftp'
